image2pipe/__init__.py
image2pipe/ffmpeg.py
image2pipe/utils.py
image2pipe-0.1.11.dist-info/LICENSE.txt
image2pipe-0.1.11.dist-info/METADATA
image2pipe-0.1.11.dist-info/WHEEL
image2pipe-0.1.11.dist-info/top_level.txt
image2pipe-0.1.11.dist-info/RECORD
