Metadata-Version: 2.1
Name: image2pipe
Version: 0.1.11
Summary: Simple ffmpeg wrapper for image2pipe which yields rawvideo frames from input video URL
Home-page: https://github.com/chexov/image2pipe
Author: Anton P. Linevich
Author-email: anton@linevich.com
License: LICENSE.txt
Keywords: ffmpeg yuv image2pipe
Platform: UNKNOWN
Requires-Python: >=3.2
Requires-Dist: tblib
Requires-Dist: numpy
Requires-Dist: websocket
